thoth_qdrant/__init__.py
thoth_qdrant/factory.py
thoth_qdrant/adapter/__init__.py
thoth_qdrant/adapter/qdrant_native.py
thoth_qdrant/core/__init__.py
thoth_qdrant/core/base.py
thoth_qdrant/core/embedding_manager.py
thoth_qdrant-1.0.0.dist-info/licenses/LICENSE.md
thoth_qdrant-1.0.0.dist-info/METADATA
thoth_qdrant-1.0.0.dist-info/WHEEL
thoth_qdrant-1.0.0.dist-info/top_level.txt
thoth_qdrant-1.0.0.dist-info/RECORD
