Metadata-Version: 2.4
Name: thoth-qdrant
Version: 1.0.0
Summary: Native Qdrant implementation for Thoth Vector Database
Author: Marco Pancotti
License-Expression: MIT
Keywords: vector database,qdrant,embeddings,thoth,ai
Classifier: Development Status :: 4 - Beta
Classifier: Intended Audience :: Developers
Classifier: Programming Language :: Python :: 3
Classifier: Programming Language :: Python :: 3.9
Classifier: Programming Language :: Python :: 3.10
Classifier: Programming Language :: Python :: 3.11
Classifier: Programming Language :: Python :: 3.12
Classifier: Topic :: Database
Classifier: Topic :: Scientific/Engineering :: Artificial Intelligence
Requires-Python: >=3.9
License-File: LICENSE.md
Requires-Dist: qdrant-client>=1.7.0
Requires-Dist: pydantic>=2.0.0
Requires-Dist: typing-extensions>=4.0.0
Provides-Extra: openai
Requires-Dist: openai>=1.0.0; extra == "openai"
Provides-Extra: cohere
Requires-Dist: cohere>=4.0.0; extra == "cohere"
Provides-Extra: mistral
Requires-Dist: mistralai>=0.0.7; extra == "mistral"
Provides-Extra: huggingface
Requires-Dist: huggingface-hub>=0.17.0; extra == "huggingface"
Requires-Dist: requests>=2.31.0; extra == "huggingface"
Provides-Extra: all-providers
Requires-Dist: openai>=1.0.0; extra == "all-providers"
Requires-Dist: cohere>=4.0.0; extra == "all-providers"
Requires-Dist: mistralai>=0.0.7; extra == "all-providers"
Requires-Dist: huggingface-hub>=0.17.0; extra == "all-providers"
Requires-Dist: requests>=2.31.0; extra == "all-providers"
Provides-Extra: test
Requires-Dist: pytest>=7.0.0; extra == "test"
Requires-Dist: pytest-asyncio>=0.21.0; extra == "test"
Requires-Dist: pytest-cov>=4.0.0; extra == "test"
Requires-Dist: python-dotenv>=1.0.0; extra == "test"
Provides-Extra: dev
Requires-Dist: black>=23.0.0; extra == "dev"
Requires-Dist: isort>=5.12.0; extra == "dev"
Requires-Dist: mypy>=1.0.0; extra == "dev"
Requires-Dist: ruff>=0.1.0; extra == "dev"
Dynamic: license-file
